{"additions":[],"category":"chinese-seafood","categoryurl":"http://localhost:1313/chinese-seafood/","content":"\u003cp\u003eSliced fish filet seasoned, coated \u0026amp; deep fried with a sweet and pungent sauce; pineapple\u003c/p\u003e\n","cookingmethods":[],"date":"2025-01-20T00:00:00Z","daysofweek":[],"desc":"\u003cp\u003eSliced fish filet seasoned, coated \u0026amp; deep fried with a sweet and pungent sauce; pineapple\u003c/p\u003e","events":[],"flavours":["-"],"images":[],"ingredients":[],"items":["-","-",80],"modifications":[],"name":"Sweet \u0026 Sour Fish","sideoptions":[],"sides":[],"sizes":["-"],"tags":["Main","Seafood"],"title":"Sweet \u0026 Sour Fish","types":[],"url":"/chinese-seafood/sweet-sour-fish/","weight":251}